amethyst/__init__.py
amethyst/amethyst.py
amethyst/error.py
amethyst/util.py
amethyst/widget/__init__.py
amethyst/widget/command.py
amethyst/widget/event/__init__.py
amethyst/widget/event/event.py
amethyst/widget/event/library.py
amethyst/widget/menu.py
amethyst/widget/schedule.py
discord_amethyst-2.0.0.dist-info/LICENCE
discord_amethyst-2.0.0.dist-info/METADATA
discord_amethyst-2.0.0.dist-info/WHEEL
discord_amethyst-2.0.0.dist-info/RECORD
