Metadata-Version: 2.1
Name: discord-amethyst
Version: 2.0.0
Summary: An opinionated extension for discord.py.
Home-page: https://github.com/NimajnebEC/discord-amethyst
License: MIT
Author: NimajnebEC
Author-email: nimajnebec@users.noreply.github.com
Requires-Python: >=3.11,<4.0
Classifier: License :: OSI Approved :: MIT License
Classifier: Programming Language :: Python :: 3
Classifier: Programming Language :: Python :: 3.11
Classifier: Programming Language :: Python :: 3.12
Requires-Dist: croniter (>=1.4.1,<2.0.0)
Requires-Dist: discord-py (>=2.3.2,<3.0.0)
Requires-Dist: dynamicpy (>=1.2.2,<2.0.0)
Requires-Dist: environ-import (>=0.1.0,<0.2.0)
Requires-Dist: lavender-logging (>=1.0.0,<2.0.0)
Project-URL: Repository, https://github.com/NimajnebEC/discord-amethyst
